yhalpha/__init__.py
yhalpha-0.0.0.dist-info/METADATA
yhalpha-0.0.0.dist-info/WHEEL
yhalpha-0.0.0.dist-info/top_level.txt
yhalpha-0.0.0.dist-info/RECORD
