Metadata-Version: 2.1
Name: yhalpha
Version: 0.0.0
Summary: Tool for airworks sdk
Home-page: UNKNOWN
Author: valuesimplex
License: UNKNOWN
Platform: UNKNOWN
Classifier: Development Status :: 3 - Alpha
Classifier: Intended Audience :: Developers
Classifier: Topic :: Software Development :: Build Tools
Classifier: License :: OSI Approved :: MIT License
Classifier: Programming Language :: Python :: 3
Requires-Python: >=3.5
Requires-Dist: pandas
Requires-Dist: requests
